owlmPy/__init__.py
owlmPy/fdtd_1d.py
owlmPy/twobytwoMatrix.py
owlmPy-0.0.4.dist-info/METADATA
owlmPy-0.0.4.dist-info/RECORD
owlmPy-0.0.4.dist-info/WHEEL
owlmPy-0.0.4.dist-info/top_level.txt
